contourpy/__init__.py
contourpy/_contourpy.cp311-win_amd64.pyd
contourpy/_version.py
contourpy/chunk.py
contourpy/enum_util.py
contourpy/py.typed
contourpy/util/__init__.py
contourpy/util/bokeh_renderer.py
contourpy/util/bokeh_util.py
contourpy/util/data.py
contourpy/util/mpl_renderer.py
contourpy/util/mpl_util.py
contourpy/util/renderer.py
contourpy-1.0.7.dist-info/LICENSE
contourpy-1.0.7.dist-info/METADATA
contourpy-1.0.7.dist-info/WHEEL
contourpy-1.0.7.dist-info/top_level.txt
contourpy-1.0.7.dist-info/RECORD
