Metadata-Version: 2.1
Name: contourpy
Version: 1.0.7
Summary: Python library for calculating contours of 2D quadrilateral grids
Author: Ian Thomas
Author-email: ianthomas23@gmail.com
License: BSD-3-Clause
Project-URL: documentation, https://contourpy.readthedocs.io
Project-URL: repository, https://github.com/contourpy/contourpy
Platform: any
Classifier: Development Status :: 5 - Production/Stable
Classifier: Intended Audience :: Developers
Classifier: Intended Audience :: Science/Research
Classifier: License :: OSI Approved :: BSD License
Classifier: Programming Language :: C++
Classifier: Programming Language :: Python :: 3
Classifier: Programming Language :: Python :: 3.8
Classifier: Programming Language :: Python :: 3.9
Classifier: Programming Language :: Python :: 3.10
Classifier: Programming Language :: Python :: 3.11
Classifier: Topic :: Scientific/Engineering :: Information Analysis
Classifier: Topic :: Scientific/Engineering :: Mathematics
Classifier: Topic :: Scientific/Engineering :: Visualization
Requires-Python: >=3.8
Provides-Extra: docs
Provides-Extra: bokeh
Provides-Extra: mypy
Provides-Extra: test
Provides-Extra: test-no-images
License-File: LICENSE
